ikku/__init__.py
ikku/bracket_state.py
ikku/node.py
ikku/parser.py
ikku/reviewer.py
ikku/scanner.py
ikku/song.py
ikku-0.1.3.dist-info/LICENSE
ikku-0.1.3.dist-info/METADATA
ikku-0.1.3.dist-info/WHEEL
ikku-0.1.3.dist-info/top_level.txt
ikku-0.1.3.dist-info/RECORD
