Metadata-Version: 2.1
Name: ikku
Version: 0.1.3
Summary: Discover haiku from text.
Home-page: https://github.com/ottanjp/ikku
Author: Yohei Kirino
Author-email: kirino.yohei@gmail.com
License: MIT
Keywords: MeCab
Platform: UNKNOWN
Classifier: Development Status :: 3 - Alpha
Classifier: License :: OSI Approved :: MIT License
Classifier: Programming Language :: Python
Classifier: Programming Language :: Python :: 3
Classifier: Programming Language :: Python :: 3.8
Classifier: Topic :: Text Processing :: Linguistic
Classifier: Topic :: Software Development :: Libraries :: Python Modules
Requires-Dist: natto-py
